seiqrdp_model/Algeria_SEIR_COVID2019_Object.py
seiqrdp_model/DataCollector.py
seiqrdp_model/Experiment.py
seiqrdp_model/SEIR_Solver.py
seiqrdp_model/__init__.py
seiqrdp_model-7.5.3.dist-info/LICENSE
seiqrdp_model-7.5.3.dist-info/METADATA
seiqrdp_model-7.5.3.dist-info/WHEEL
seiqrdp_model-7.5.3.dist-info/top_level.txt
seiqrdp_model-7.5.3.dist-info/RECORD
