Metadata-Version: 2.1
Name: seiqrdp-model
Version: 7.5.3
Summary: Computational tools to fit data, simulate and calibrate    parameters of the compartmental epidemiological SEIQRDP model.
Home-page: https://github.com/Taha-Rouabah/COVID-19
Author: T.Rouabah, N.Belaloui, A.Tounsi
Author-email: m.t.rouabah@gmail.com
License: UNKNOWN
Platform: UNKNOWN
Classifier: Programming Language :: Python :: 3
Classifier: License :: OSI Approved :: Apache Software License
Classifier: Operating System :: OS Independent
Requires-Python: >=3.6
Requires-Dist: colorama
Requires-Dist: matplotlib
Requires-Dist: numpy
Requires-Dist: pandas
Requires-Dist: psutil
Requires-Dist: scipy
